MANIFEST.in
requirements.txt
setup.py
test.txt
test_requirements.txt
version.txt
cloudshell/__init__.py
cloudshell/traffic/__init__.py
cloudshell/traffic/teravm/__init__.py
cloudshell/traffic/teravm/cleanup/__init__.py
cloudshell/traffic/teravm/cleanup/app_cleanup_handler.py
cloudshell/traffic/teravm/common/__init__.py
cloudshell/traffic/teravm/common/cloudshell_helper.py
cloudshell/traffic/teravm/common/error_messages.py
cloudshell/traffic/teravm/common/i18n.py
cloudshell/traffic/teravm/common/parsing_utilities.py
cloudshell/traffic/teravm/common/path_utilties.py
cloudshell/traffic/teravm/common/vsphere_helper.py
cloudshell/traffic/teravm/controller/__init__.py
cloudshell/traffic/teravm/controller/driver_handler.py
cloudshell/traffic/teravm/controller/port_selector_helper.py
cloudshell/traffic/teravm/controller/teravm_executive_helper.py
cloudshell/traffic/teravm/deployment/__init__.py
cloudshell/traffic/teravm/deployment/app_deployment_handler.py
cloudshell/traffic/teravm/management_assistant/__init__.py
cloudshell/traffic/teravm/management_assistant/tvm_ma.py
cloudshell/traffic/teravm/management_assistant/tvmma_controller.py
cloudshell/traffic/teravm/models/__init__.py
cloudshell/traffic/teravm/models/deployment_configuration.py
cloudshell/traffic/teravm/models/tvm_ma_model.py
cloudshell/traffic/teravm/models/tvm_request.py
cloudshell/traffic/teravm/test_module/__init__.py
cloudshell/traffic/teravm/test_module/driver_handler.py
cloudshell_traffic_teravm.egg-info/PKG-INFO
cloudshell_traffic_teravm.egg-info/SOURCES.txt
cloudshell_traffic_teravm.egg-info/dependency_links.txt
cloudshell_traffic_teravm.egg-info/requires.txt
cloudshell_traffic_teravm.egg-info/top_level.txt