Metadata-Version: 1.1
Name: cloudshell-traffic-teravm
Version: 1.1.0
Summary: A repository for deploying and managing TeraVM controllers and test modules.
Home-page: UNKNOWN
Author: Quali
Author-email: support@qualisystems.com
License: UNKNOWN
Keywords: sandbox cloud virtualization teravm tvm traffic cloudshell
Platform: UNKNOWN
Classifier: Development Status :: 4 - Beta
Classifier: Topic :: Software Development :: Libraries
Classifier: License :: OSI Approved :: Apache Software License
